{
  "store_info": {
    "name": "京都柚子豚骨拉麵 中山本店",
    "address": "104台北市中山區長安西路19巷2弄23號",
    "phone": "",
    "open_time": "星期六、11:30 到 20:00; 星期日、11:30 到 20:00; 星期一、11:30 到 14:00、17:00 到 20:00; 星期二、11:30 到 14:00、17:00 到 20:00; 星期三、11:30 到 14:00、17:00 到 20:00; 星期四、11:30 到 14:00、17:00 到 20:00; 星期五 (端午節 (補假))、11:30 到 14:30、17:00 到 20:00、營業時間可能不同. 隱藏本週營業時間",
    "rating": 4.5,
    "keywords": [
      "豚骨",
      "黑蒜"
    ],
    "latitude": 25.0510279,
    "longitude": 121.520426,
    "reviews": [
      "中山有名拉麵都吃過一輪了\n但老實說我對拉麵算是又愛又恨\n拉麵非常容易吃到一半就會覺得膩 …",
      "位在距離中山捷運站走路約5分鐘距離的日式拉麵店\n總體來說：好吃，對女生來說份量也夠～ …",
      "拉麵味道還不錯，湯底挑選偏淡的，但風味不減，可以喝出濃濃的豚汁，是好吃的拉麵，好評價老闆會送冰淇淋（此篇評論沒有參加）。以單價 $250沒有筍跟蛋，不是預期清爽的柚子味拉麵，而不能加麵會覺得有點空虛。"
    ],
    "menu_image": "Web Crawler/ramin/images\\京都柚子豚_menu.jpg"
  }
}